LICENSE
README.md
setup.py
py_prompt_ai/__init__.py
py_prompt_ai/prompt_manager.py
py_prompt_ai.egg-info/PKG-INFO
py_prompt_ai.egg-info/SOURCES.txt
py_prompt_ai.egg-info/dependency_links.txt
py_prompt_ai.egg-info/requires.txt
py_prompt_ai.egg-info/top_level.txt
tests/__init__.py
tests/test_prompt_manager.py